main.py
tui_reader-1.0.0.dist-info/licenses/LICENSE
tui_reader-1.0.0.dist-info/METADATA
tui_reader-1.0.0.dist-info/WHEEL
tui_reader-1.0.0.dist-info/entry_points.txt
tui_reader-1.0.0.dist-info/top_level.txt
tui_reader-1.0.0.dist-info/RECORD
