Metadata-Version: 2.4
Name: tui-reader
Version: 1.0.0
Summary: A terminal-based reader for TXT, MD, and PDF files with themes and voice control
Home-page: https://github.com/alaotach/tui-reader
Author: AlAoTach
Author-email: Your Name <your.email@example.com>
License: MIT
Project-URL: Homepage, https://github.com/yourusername/tui-reader
Project-URL: Repository, https://github.com/yourusername/tui-reader
Classifier: Development Status :: 4 - Beta
Classifier: Intended Audience :: End Users/Desktop
Classifier: Topic :: Text Editors
Classifier: License :: OSI Approved :: MIT License
Classifier: Programming Language :: Python :: 3
Classifier: Programming Language :: Python :: 3.8
Classifier: Programming Language :: Python :: 3.9
Classifier: Programming Language :: Python :: 3.10
Classifier: Programming Language :: Python :: 3.11
Classifier: Operating System :: OS Independent
Requires-Python: >=3.8
License-File: LICENSE
Requires-Dist: textual>=0.40.0
Requires-Dist: pdfminer.six>=20221105
Provides-Extra: voice
Requires-Dist: vosk>=0.3.45; extra == "voice"
Requires-Dist: pyaudio>=0.2.13; extra == "voice"
Dynamic: author
Dynamic: home-page
Dynamic: license-file
Dynamic: requires-python
